{
  "updated": "2026-05-11T09:36:14.064606-07:00",
  "score": 85,
  "prices": {
    "SPY": {
      "price": 740.28,
      "prev": 737.74,
      "change": 0.34
    },
    "QQQ": {
      "price": 714.13,
      "prev": 712.11,
      "change": 0.28
    },
    "SOXX": {
      "price": 530.82,
      "prev": 522.0,
      "change": 1.69
    },
    "AAPL": {
      "price": 292.27,
      "prev": 293.86,
      "change": -0.54
    },
    "NVDA": {
      "price": 221.71,
      "prev": 215.05,
      "change": 3.1
    },
    "MU": {
      "price": 792.44,
      "prev": 757.35,
      "change": 4.63
    },
    "XLI": {
      "price": 174.95,
      "prev": 173.4,
      "change": 0.89
    },
    "XLV": {
      "price": 143.23,
      "prev": 143.77,
      "change": -0.38
    },
    "IAU": {
      "price": 88.78,
      "prev": 88.8,
      "change": -0.02
    },
    "KBWB": {
      "price": 84.36,
      "prev": 85.09,
      "change": -0.86
    },
    "BTC": {
      "price": 81890.0,
      "prev": 82199.99,
      "change": -0.38
    }
  },
  "macro": {
    "VIX": 17.99,
    "VIX_CHG": 4.65,
    "GOLD": 4734.9,
    "GOLD_CHG": 0.0,
    "OIL": 98.6,
    "OIL_CHG": 0.0,
    "YIELD": 4.39,
    "YIELD_CHG": 0.69,
    "USD": 97.92,
    "USD_CHG": 0.0
  },
  "levels": {
    "SPY": {
      "s1": 715,
      "s2": 670,
      "r1": 775,
      "r2": 815,
      "ma20": 715.77,
      "ma50": 684.85,
      "ma200": 671.11
    },
    "QQQ": {
      "s1": 665,
      "s2": 605,
      "r1": 750,
      "r2": 785,
      "ma20": 665.63,
      "ma50": 622.82,
      "ma200": 606.89
    },
    "SOXX": {
      "s1": 455,
      "s2": 315,
      "r1": 555,
      "r2": 585,
      "ma20": 453.19,
      "ma50": 386.63,
      "ma200": 316.93
    },
    "AAPL": {
      "s1": 275,
      "s2": 255,
      "r1": 305,
      "r2": 320,
      "ma20": 274.86,
      "ma50": 263.36,
      "ma200": 257.15
    },
    "NVDA": {
      "s1": 205,
      "s2": 185,
      "r1": 235,
      "r2": 245,
      "ma20": 204.8,
      "ma50": 189.54,
      "ma200": 184.96
    },
    "MU": {
      "s1": 545,
      "s2": 310,
      "r1": 830,
      "r2": 875,
      "ma20": 543.69,
      "ma50": 456.5,
      "ma200": 293.85
    },
    "XLI": {
      "s1": 175,
      "s2": 160,
      "r1": 180,
      "r2": 185,
      "ma20": 172.73,
      "ma50": 169.17,
      "ma200": 159.35
    },
    "XLV": {
      "s1": 135,
      "s2": 130,
      "r1": 150,
      "r2": 155,
      "ma20": 145.52,
      "ma50": 147.53,
      "ma200": 146.36
    },
    "IAU": {
      "s1": 85.1,
      "s2": 80.9,
      "r1": 91.0,
      "r2": 95.5,
      "ma20": 88.33,
      "ma50": 89.76,
      "ma200": 80.9
    },
    "KBWB": {
      "s1": 82.2,
      "s2": 79.9,
      "r1": 88.2,
      "r2": 92.7,
      "ma20": 86.4,
      "ma50": 82.16,
      "ma200": 79.91
    },
    "BTC": {
      "s1": 79000,
      "s2": 70500,
      "r1": 86000,
      "r2": 90500,
      "ma20": 78922.08,
      "ma50": 74194.42,
      "ma200": 82584.58
    }
  },
  "technicals": {
    "SPY": {
      "rsi": 80.8,
      "trend": "UPTREND",
      "ma50": 684.85,
      "ma200": 671.11
    },
    "QQQ": {
      "rsi": 86.8,
      "trend": "UPTREND",
      "ma50": 622.82,
      "ma200": 606.89
    },
    "SOXX": {
      "rsi": 78.6,
      "trend": "UPTREND",
      "ma50": 386.63,
      "ma200": 316.93
    },
    "AAPL": {
      "rsi": 77.4,
      "trend": "UPTREND",
      "ma50": 263.36,
      "ma200": 257.15
    },
    "NVDA": {
      "rsi": 66.1,
      "trend": "UPTREND",
      "ma50": 189.54,
      "ma200": 184.96
    },
    "MU": {
      "rsi": 89.2,
      "trend": "UPTREND",
      "ma50": 456.5,
      "ma200": 293.85
    },
    "XLI": {
      "rsi": 56.4,
      "trend": "UPTREND",
      "ma50": 169.17,
      "ma200": 159.35
    },
    "XLV": {
      "rsi": 38.8,
      "trend": "SIDEWAYS",
      "ma50": 147.53,
      "ma200": 146.36
    },
    "IAU": {
      "rsi": 52.9,
      "trend": "SIDEWAYS",
      "ma50": 89.76,
      "ma200": 80.9
    },
    "KBWB": {
      "rsi": 36.5,
      "trend": "UPTREND",
      "ma50": 82.16,
      "ma200": 79.91
    },
    "BTC": {
      "rsi": 70.1,
      "trend": "SIDEWAYS",
      "ma50": 74194.42,
      "ma200": 82584.58
    }
  },
  "avg_costs": {
    "SPY": 673.15,
    "QQQ": 597.57,
    "SOXX": 330.78,
    "AAPL": 257.3,
    "NVDA": 181.46,
    "MU": 376.93,
    "XLI": 169.1,
    "XLV": 156.27,
    "IAU": 93.76,
    "KBWB": 80.14,
    "BTC": 71896
  }
}