{
  "updated": "2026-05-04T10:44:35.244743-07:00",
  "score": 85,
  "prices": {
    "SPY": {
      "price": 718.26,
      "prev": 720.0,
      "change": -0.24
    },
    "QQQ": {
      "price": 672.86,
      "prev": 673.55,
      "change": -0.1
    },
    "SOXX": {
      "price": 462.67,
      "prev": 465.0,
      "change": -0.5
    },
    "AAPL": {
      "price": 277.08,
      "prev": 280.1,
      "change": -1.08
    },
    "NVDA": {
      "price": 197.7,
      "prev": 198.13,
      "change": -0.22
    },
    "MU": {
      "price": 577.21,
      "prev": 539.91,
      "change": 6.91
    },
    "XLI": {
      "price": 171.54,
      "prev": 172.91,
      "change": -0.79
    },
    "XLV": {
      "price": 144.73,
      "prev": 145.65,
      "change": -0.63
    },
    "IAU": {
      "price": 85.14,
      "prev": 86.82,
      "change": -1.94
    },
    "KBWB": {
      "price": 85.51,
      "prev": 87.66,
      "change": -2.45
    },
    "BTC": {
      "price": 80293.51,
      "prev": 78558.88,
      "change": 2.21
    }
  },
  "macro": {
    "VIX": 18.12,
    "VIX_CHG": 6.65,
    "GOLD": 4535.5,
    "GOLD_CHG": 0.0,
    "OIL": 105.45,
    "OIL_CHG": 0.0,
    "YIELD": 4.44,
    "YIELD_CHG": 1.37,
    "USD": 98.42,
    "USD_CHG": 0.0
  },
  "levels": {
    "SPY": {
      "s1": 700,
      "s2": 670,
      "r1": 755,
      "r2": 790,
      "ma20": 701.47,
      "ma50": 680.09,
      "ma200": 668.42
    },
    "QQQ": {
      "s1": 640,
      "s2": 605,
      "r1": 705,
      "r2": 740,
      "ma20": 642.41,
      "ma50": 613.64,
      "ma200": 603.43
    },
    "SOXX": {
      "s1": 420,
      "s2": 310,
      "r1": 485,
      "r2": 510,
      "ma20": 420.4,
      "ma50": 371.88,
      "ma200": 310.35
    },
    "AAPL": {
      "s1": 265,
      "s2": 255,
      "r1": 290,
      "r2": 305,
      "ma20": 267.27,
      "ma50": 261.47,
      "ma200": 255.24
    },
    "NVDA": {
      "s1": 185,
      "s2": 185,
      "r1": 205,
      "r2": 215,
      "ma20": 198.23,
      "ma50": 187.31,
      "ma200": 183.96
    },
    "MU": {
      "s1": 470,
      "s2": 310,
      "r1": 605,
      "r2": 635,
      "ma20": 471.74,
      "ma50": 428.56,
      "ma200": 279.18
    },
    "XLI": {
      "s1": 170,
      "s2": 160,
      "r1": 175,
      "r2": 185,
      "ma20": 171.75,
      "ma50": 169.33,
      "ma200": 158.76
    },
    "XLV": {
      "s1": 145,
      "s2": 135,
      "r1": 150,
      "r2": 155,
      "ma20": 146.45,
      "ma50": 148.86,
      "ma200": 146.05
    },
    "IAU": {
      "s1": 82.7,
      "s2": 80.3,
      "r1": 91.1,
      "r2": 95.7,
      "ma20": 88.63,
      "ma50": 90.75,
      "ma200": 80.29
    },
    "KBWB": {
      "s1": 81.9,
      "s2": 79.6,
      "r1": 88.2,
      "r2": 92.6,
      "ma20": 86.04,
      "ma50": 81.92,
      "ma200": 79.59
    },
    "BTC": {
      "s1": 77000,
      "s2": 66500,
      "r1": 84500,
      "r2": 88500,
      "ma20": 77027.73,
      "ma50": 72799.26,
      "ma200": 83546.47
    }
  },
  "technicals": {
    "SPY": {
      "rsi": 72.3,
      "trend": "UPTREND",
      "ma50": 680.09,
      "ma200": 668.42
    },
    "QQQ": {
      "rsi": 78.9,
      "trend": "UPTREND",
      "ma50": 613.64,
      "ma200": 603.43
    },
    "SOXX": {
      "rsi": 77.1,
      "trend": "UPTREND",
      "ma50": 371.88,
      "ma200": 310.35
    },
    "AAPL": {
      "rsi": 66.0,
      "trend": "UPTREND",
      "ma50": 261.47,
      "ma200": 255.24
    },
    "NVDA": {
      "rsi": 51.2,
      "trend": "UPTREND",
      "ma50": 187.31,
      "ma200": 183.96
    },
    "MU": {
      "rsi": 77.5,
      "trend": "UPTREND",
      "ma50": 428.56,
      "ma200": 279.18
    },
    "XLI": {
      "rsi": 46.3,
      "trend": "UPTREND",
      "ma50": 169.33,
      "ma200": 158.76
    },
    "XLV": {
      "rsi": 37.5,
      "trend": "SIDEWAYS",
      "ma50": 148.86,
      "ma200": 146.05
    },
    "IAU": {
      "rsi": 28.6,
      "trend": "SIDEWAYS",
      "ma50": 90.75,
      "ma200": 80.29
    },
    "KBWB": {
      "rsi": 49.1,
      "trend": "UPTREND",
      "ma50": 81.92,
      "ma200": 79.59
    },
    "BTC": {
      "rsi": 68.3,
      "trend": "SIDEWAYS",
      "ma50": 72799.26,
      "ma200": 83546.47
    }
  },
  "avg_costs": {
    "SPY": 673.15,
    "QQQ": 597.57,
    "SOXX": 330.78,
    "AAPL": 257.3,
    "NVDA": 181.46,
    "MU": 376.93,
    "XLI": 169.1,
    "XLV": 156.27,
    "IAU": 93.76,
    "KBWB": 80.14,
    "BTC": 71896
  }
}